GA_img_help/GA_img_help.py
GA_img_help/__init__.py
GA_img_recovery/GA_img_recovery.py
GA_img_recovery/__init__.py
GA_img_visualize/GA_img_visualize.py
GA_img_visualize/__init__.py
model_1/__init__.py
model_1/model_1.py
model_2/__init__.py
model_2/model_2.py
model_3/__init__.py
model_3/model_3.py
GA_IMG_Classification-0.0.0.dist-info/LICENSE.txt
GA_IMG_Classification-0.0.0.dist-info/METADATA
GA_IMG_Classification-0.0.0.dist-info/WHEEL
GA_IMG_Classification-0.0.0.dist-info/top_level.txt
GA_IMG_Classification-0.0.0.dist-info/RECORD
