Metadata-Version: 2.1
Name: GA-IMG-Classification
Version: 0.0.0
Summary: GA for best models for image classification
Author: Svetlana Luneva
Author-email: mibellisvetlana@gmail.com
Classifier: Programming Language :: Python :: 3
Classifier: License :: OSI Approved :: MIT License
Classifier: Operating System :: OS Independent
Requires-Python: >=3.6
License-File: LICENSE.txt
